swine/__init__.py
swine/component/__init__.py
swine/component/sprite_renderer.py
swine/component/transform.py
swine/component/viewport.py
swine/component/physics/__init__.py
swine/component/physics/rigid_body.py
swine/component/physics/collider/__init__.py
swine/component/physics/collider/base_collider.py
swine/component/physics/collider/box_collider.py
swine/component/physics/collider/polygon_collider.py
swine/component/quicktime/__init__.py
swine/component/quicktime/quicktime_hold.py
swine/component/quicktime/quicktime_mash.py
swine/graphics/__init__.py
swine/graphics/sprite.py
swine/gui/__init__.py
swine/gui/button.py
swine/gui/canvas.py
swine/gui/checkbox.py
swine/gui/dropdown.py
swine/gui/input.py
swine/gui/label.py
swine/gui/menu.py
swine/gui/slider.py
swine/gui/widget.py
swine/gui/window.py
swine/input/__init__.py
swine/input/empty_controller.py
swine/input/gamecube_controller.py
swine/input/input_manager.py
swine/input/playstation_controller.py
swine/input/xbox_controller.py
swine/input/handler/__init__.py
swine/input/handler/joystick_state_handler.py
swine/input/handler/mouse_state_handler.py
swine/object/__init__.py
swine/object/anchors.py
swine/object/component.py
swine/object/game_object.py
swine/terminal/__init__.py
swine/terminal/commands/__init__.py
swine/terminal/commands/command.py
swine/terminal/commands/command_manager.py
swine/terminal/commands/standard/__init__.py
swine/terminal/commands/standard/command_commands.py
swine/terminal/commands/standard/command_help.py
swine/terminal/window/__init__.py
swine/terminal/window/terminal_window.py
swine/window/__init__.py
swine/window/layer.py
swine/window/mainloop.py
swine/window/scene.py
swine/window/window.py
swine-2.6.1.dist-info/DESCRIPTION.rst
swine-2.6.1.dist-info/METADATA
swine-2.6.1.dist-info/RECORD
swine-2.6.1.dist-info/WHEEL
swine-2.6.1.dist-info/metadata.json
swine-2.6.1.dist-info/top_level.txt
