Metadata-Version: 2.0
Name: swine
Version: 2.6.1
Summary: A Python game engine
Home-page: https://github.com/SwineProject/swine
Author: DeflatedPickle
Author-email: UNKNOWN
License: MIT
Keywords: swine,game,engine,game engine
Platform: UNKNOWN
Classifier: Intended Audience :: Developers
Classifier: License :: OSI Approved :: MIT License
Classifier: Programming Language :: Python :: 3.4
Classifier: Programming Language :: Python :: 3.5
Classifier: Programming Language :: Python :: 3.6
Requires-Dist: pyglet
Requires-Dist: pymunk
Requires-Dist: felyne
